zlogin/__init__.py
zlogin/zlogin.py
zlogin-0.0.8.dist-info/LICENSE
zlogin-0.0.8.dist-info/WHEEL
zlogin-0.0.8.dist-info/METADATA
zlogin-0.0.8.dist-info/RECORD
