Metadata-Version: 2.1
Name: zlogin
Version: 0.0.8
Summary: Zerodha Login Automation - Selenium Based
Home-page: https://github.com/prabhatrastogik/zlogin
License: MIT
Keywords: Zerodha,Automated Login,Selenium Login
Author: Prabhat Rastogi
Author-email: prabhatrastogik@gmail.com
Requires-Python: >=3.10,<4.0
Classifier: License :: OSI Approved :: MIT License
Classifier: Programming Language :: Python :: 3
Classifier: Programming Language :: Python :: 3.10
Classifier: Programming Language :: Python :: 3.11
Requires-Dist: boto3
Requires-Dist: kiteconnect
Requires-Dist: pyotp
Project-URL: Repository, https://github.com/prabhatrastogik/zlogin
